dismew/__about__.py
dismew/__init__.py
dismew/app.py
dismew/entry_points.py
dismew/enums.py
dismew/errors.py
dismew/pattern_file_handler.py
dismew/pattern_handler.py
dismew/reactives.py
dismew/patterns/aws
dismew/patterns/bacula
dismew/patterns/bind
dismew/patterns/bro
dismew/patterns/exim
dismew/patterns/firewalls
dismew/patterns/grok-patterns
dismew/patterns/haproxy
dismew/patterns/httpd
dismew/patterns/java
dismew/patterns/junos
dismew/patterns/linux-syslog
dismew/patterns/maven
dismew/patterns/mcollective
dismew/patterns/mongodb
dismew/patterns/nagios
dismew/patterns/postgresql
dismew/patterns/rails
dismew/patterns/redis
dismew/patterns/ruby
dismew/patterns/squid
dismew/patterns/zeek
dismew/screens/__init__.py
dismew/screens/pattern_file_selector.py
dismew/styles/load.tcss
dismew/styles/main.tcss
dismew-0.2.0.dist-info/METADATA
dismew-0.2.0.dist-info/WHEEL
dismew-0.2.0.dist-info/entry_points.txt
dismew-0.2.0.dist-info/licenses/LICENSE
dismew-0.2.0.dist-info/RECORD
