Metadata-Version: 2.4
Name: dismew
Version: 0.2.0
Summary: Debugger tool for Logstash's Grok parsing language.
Project-URL: Documentation, https://codeberg.org/spuzkov/dismew#readme
Project-URL: Issues, https://codeberg.org/spuzkov/dismew/issues
Project-URL: Source, https://codeberg.org/spuzkov/dismew
Author-email: spuzkov <spuzkov@noreply.codeberg.org>
License-Expression: GPL-3.0-or-later
License-File: LICENSE
Keywords: Debugger,Grok,TUI,Textualize
Classifier: Development Status :: 4 - Beta
Classifier: Environment :: Console
Classifier: Programming Language :: Python
Classifier: Programming Language :: Python :: 3.11
Classifier: Programming Language :: Python :: Implementation :: CPython
Classifier: Programming Language :: Python :: Implementation :: PyPy
Requires-Python: >=3.11
Requires-Dist: pytest==8.4.1
Requires-Dist: textual-dev==1.7.0
Requires-Dist: textual[syntax]==5.2.0
